seqript/__init__.py
seqript/seqript.py
seqript/engine/__init__.py
seqript/engine/cmd.py
seqript/engine/nop.py
seqript/engine/par.py
seqript/engine/seq.py
seqript/engine/contrib/__init__.py
seqript/engine/contrib/comment.py
seqript/engine/contrib/sleep.py
seqript/util/__init__.py
seqript/util/expand_variable.py
seqript-1.0.0.dist-info/licenses/LICENSE
seqript-1.0.0.dist-info/METADATA
seqript-1.0.0.dist-info/WHEEL
seqript-1.0.0.dist-info/top_level.txt
seqript-1.0.0.dist-info/RECORD
