Metadata-Version: 2.4
Name: Seqript
Version: 1.0.0
Summary: Seqript is a recursive structured command engine.
Home-page: https://github.com/Tarcadia/Seqript
Author: Tarcadia
Author-email: dont@email.me
License: MIT
Project-URL: Bug Reports, https://github.com/Tarcadia/Seqript/issues
Project-URL: Source, https://github.com/Tarcadia/Seqript
Keywords: sequential,sarallelscript,Tarcadia
Classifier: Development Status :: 2 - Pre-Alpha
Classifier: Environment :: Console
Classifier: Intended Audience :: Developers
Classifier: Programming Language :: Python :: 3.11
Classifier: Operating System :: OS Independent
Classifier: Typing :: Typed
Requires-Python: >=3.11, <4
License-File: LICENSE
Dynamic: author
Dynamic: author-email
Dynamic: classifier
Dynamic: description
Dynamic: description-content-type
Dynamic: home-page
Dynamic: keywords
Dynamic: license
Dynamic: license-file
Dynamic: project-url
Dynamic: requires-python
Dynamic: summary
